basic_image_preprocessing/__init__.py
basic_image_preprocessing/examples/Basic Image Processing - Conventional Methods.ipynb
basic_image_preprocessing/examples/Basic Image Processing - Edge Detection.ipynb
basic_image_preprocessing/examples/Basic Image Processing - Frequency Noise Filtering.ipynb
basic_image_preprocessing/examples/Basic Image Processing - Spatial Noise Filtering.ipynb
basic_image_preprocessing/examples/Basic Image Processing - Traditional Methods.ipynb
basic_image_preprocessing/exception/custom_exception.py
basic_image_preprocessing/image_enhancement/conventional/conventional.py
basic_image_preprocessing/image_enhancement/edge_detection/edge_detection.py
basic_image_preprocessing/image_enhancement/noise_filtering/frequency_filtering/frequency_filtering.py
basic_image_preprocessing/image_enhancement/noise_filtering/spatial_filtering/spatial_filtering.py
basic_image_preprocessing/image_enhancement/traditional/traditional.py
basic_image_preprocessing/utility/utlity.py
basic_image_preprocessing-1.0.7.dist-info/LICENSE
basic_image_preprocessing-1.0.7.dist-info/METADATA
basic_image_preprocessing-1.0.7.dist-info/WHEEL
basic_image_preprocessing-1.0.7.dist-info/RECORD
