Metadata-Version: 2.1
Name: basic_image_preprocessing
Version: 1.0.7
Summary: A complete package to perform a list of simple manual and package based image preprocessing techniques
Home-page: https://github.com/thivagar-manickam/image_preprocessing
License: MIT
Keywords: Image preprocessing,Basic Image preprocessing,Linear methods,Algorithm based preprocessing,Noise filtering,Frequency based transformation,Edge detection
Author: Saivijaay
Requires-Python: >=3.8
Classifier: License :: OSI Approved :: MIT License
Classifier: Programming Language :: Python :: 3
Classifier: Programming Language :: Python :: 3.8
Classifier: Programming Language :: Python :: 3.9
Classifier: Programming Language :: Python :: 3.10
Classifier: Programming Language :: Python :: 3.11
Classifier: Programming Language :: Python :: 3.12
Requires-Dist: PyWavelets (==1.4.1)
Requires-Dist: image_frequency_analysis (==0.2.7)
Requires-Dist: matplotlib (>=3.5.0)
Requires-Dist: numpy (>=1.21.4)
Requires-Dist: opencv-python (>=4.5.1.48)
Requires-Dist: pandas (>=1.3.5)
Project-URL: Repository, https://github.com/thivagar-manickam/image_preprocessing
